vici/__init__.py
vici/command_wrappers.py
vici/exception.py
vici/protocol.py
vici/session.py
vici-6.0.1.dist-info/LICENSE
vici-6.0.1.dist-info/METADATA
vici-6.0.1.dist-info/WHEEL
vici-6.0.1.dist-info/top_level.txt
vici-6.0.1.dist-info/RECORD
